nbdefs2py/__about__.py
nbdefs2py/__init__.py
nbdefs2py/__main__.py
nbdefs2py/funcs.py
nbdefs2py/io.py
nbdefs2py/py.typed
nbdefs2py-0.1.3.dist-info/METADATA
nbdefs2py-0.1.3.dist-info/WHEEL
nbdefs2py-0.1.3.dist-info/licenses/LICENSE
nbdefs2py-0.1.3.dist-info/RECORD
