Metadata-Version: 2.1
Name: nbdefs2py
Version: 0.1.3
Project-URL: Documentation, https://github.com/datarootsio/nbdefs2py#readme
Project-URL: Issues, https://github.com/datarootsio/nbdefs2py/issues
Project-URL: Source, https://github.com/datarootsio/nbdefs2py
Author-email: Murilo Cunha <murilo@dataroots.io>
License-Expression: MIT
License-File: LICENSE
Classifier: Development Status :: 4 - Beta
Classifier: Programming Language :: Python
Classifier: Programming Language :: Python :: 3.8
Classifier: Programming Language :: Python :: 3.9
Classifier: Programming Language :: Python :: 3.10
Classifier: Programming Language :: Python :: 3.11
Classifier: Programming Language :: Python :: Implementation :: CPython
Classifier: Programming Language :: Python :: Implementation :: PyPy
Requires-Python: >=3.8
Requires-Dist: nbformat>=5.7
